{
  "schemaVersion": "2.0",
  "meta": {
    "title": "Rethinking Animal Play"
  },
  "speech": {
    "enabled": true
  },
  "article": {
    "title": "Rethinking Animal Play: The Science of Zoo Enrichment",
    "paragraphs": [
      {
        "id": "p1",
        "en": {
          "text": "Keeping wild animals in captivity has always been a complex scientific issue. While modern zoos aim to protect species that human activities endanger in the wild, providing a healthy mental state for these animals is highly challenging. In the past, people naturally believed that putting animals in lavish enclosures with plenty of free food would ease their lives and make them happy. However, animal psychologists now confirm that this idea can easily misguide the public. A completely effortless life actually harms an animal’s mental well-being, leading to severe boredom and stress.",
          "highlights": [
            {
              "start": 24,
              "end": 33,
              "key": "captivity"
            },
            {
              "start": 141,
              "end": 149,
              "key": "endanger"
            },
            {
              "start": 300,
              "end": 306,
              "key": "lavish"
            },
            {
              "start": 349,
              "end": 353,
              "key": "ease"
            },
            {
              "start": 421,
              "end": 428,
              "key": "confirm"
            },
            {
              "start": 455,
              "end": 463,
              "key": "misguide"
            }
          ]
        },
        "zh": "将野生动物置于圈养环境中，一直是一个复杂的科学议题。虽然现代动物园致力于保护那些在野外因人类活动而受到威胁的物种，但要让这些动物保持健康的心理状态却极具挑战。过去，人们很自然地认为，只要把动物安置在奢华的围栏里，再提供充足且免费的食物，就能缓解它们的生活压力，让它们过得幸福。然而，动物心理学家如今已经证实，这种想法很容易误导公众。事实上，一种毫不费力的生活反而会损害动物的心理健康，带来严重的无聊与压力。"
      },
      {
        "id": "p2",
        "en": {
          "text": "To alleviate this stress, scientists introduced a concept called \"environmental enrichment.\" The primary goal is to motivate animals to use their natural survival instincts, just as they would in the forest. Surprisingly, the most effective enrichment tools are not expensive technological devices. Zoo keepers often use clean, safe materials that might otherwise go to a local landfill, such as cardboard boxes, old clothes, or plastic pipes. Instead of treating these items as useless trash, caretakers creatively craft them into complex \"puzzle feeders\".",
          "highlights": [
            {
              "start": 3,
              "end": 12,
              "key": "alleviate"
            },
            {
              "start": 116,
              "end": 124,
              "key": "motivate"
            },
            {
              "start": 231,
              "end": 240,
              "key": "effective"
            },
            {
              "start": 378,
              "end": 386,
              "key": "landfill"
            },
            {
              "start": 487,
              "end": 492,
              "key": "trash"
            },
            {
              "start": 516,
              "end": 521,
              "key": "craft"
            }
          ]
        },
        "zh": "为了缓解这种压力，科学家提出了“环境丰富化”这一概念。它的首要目标，是激发动物重新使用自身原有的生存本能，就像它们在森林中那样。令人惊讶的是，最有效的丰富化工具，并不是昂贵的高科技设备。动物园饲养员常常会使用那些原本可能被送往垃圾填埋场的干净、安全材料，比如纸箱、旧衣服或塑料管。照护人员并不会把这些东西当作无用的垃圾，而是创造性地将它们制作成复杂的“玩具喂食器”。"
      },
      {
        "id": "p3",
        "en": {
          "text": "These puzzles require animals to work for their meals. For example, monkeys might be given a wooden box where they must use sticks to probe hidden holes to find sweet treats. This mental workout keeps their brains active. Furthermore, social learning plays a huge role. When one clever individual figures out how to open a puzzle, its peers will watch closely and copy the behavior. This social interaction not only passes on knowledge but also strengthens group loyalty and emotional bonds, perfectly mirroring how wild groups operate.",
          "highlights": [
            {
              "start": 134,
              "end": 139,
              "key": "probe"
            },
            {
              "start": 335,
              "end": 340,
              "key": "peers"
            },
            {
              "start": 463,
              "end": 470,
              "key": "loyalty"
            }
          ]
        },
        "zh": "这些谜题要求动物必须为获得食物付出努力。比如，猴子可能会拿到一个木箱，它们必须用木棍去探查隐藏的小洞，才能找到甜食。这样的脑力锻炼能让它们的大脑保持活跃。此外，社会学习也在其中发挥着巨大作用。当一个聪明的个体率先弄明白如何打开谜题时，它的同伴就会仔细观察并模仿这种行为。这种社会互动不仅传播了知识，也强化了群体的忠诚关系与情感纽带，恰好映照出野外群体原本的运作方式。"
      },
      {
        "id": "p4",
        "en": {
          "text": "Ultimately, allowing animals to take charge of their own daily activities makes them significantly healthier. It proves a counter-intuitive philosophical point: a perfect, stress-free life without challenges is not always a good life. By introducing small, manageable difficulties, scientists help captive animals maintain their wild and brilliant minds.",
          "highlights": [
            {
              "start": 37,
              "end": 43,
              "key": "charge"
            }
          ]
        },
        "zh": "归根结底，让动物重新掌控自己的日常活动，会让它们明显更健康。这也证明了一个有些反直觉的哲学判断：一种毫无挑战、毫无压力的完美生活，并不总是一种真正的好生活。通过引入小而可控的困难，科学家得以帮助圈养动物维持那种属于野性的、灵敏而聪慧的心智。"
      }
    ]
  },
  "vocab": [
    {
      "key": "captivity",
      "pos": "n.",
      "def": "The condition of being imprisoned or confined.",
      "trans": "圈养，囚禁",
      "speakText": "captivity"
    },
    {
      "key": "endanger",
      "pos": "v.",
      "def": "Put (someone or something) at risk of danger.",
      "trans": "危及，使濒危",
      "speakText": "endanger"
    },
    {
      "key": "lavish",
      "pos": "adj.",
      "def": "Sumptuously rich, elaborate, or luxurious.",
      "trans": "奢华的，极其丰富的",
      "speakText": "lavish"
    },
    {
      "key": "ease",
      "pos": "v.",
      "def": "Make (something unpleasant or intense) less serious or severe.",
      "trans": "减轻，缓解",
      "speakText": "ease"
    },
    {
      "key": "confirm",
      "pos": "v.",
      "def": "Establish the truth or correctness of.",
      "trans": "确认，证实",
      "speakText": "confirm"
    },
    {
      "key": "misguide",
      "pos": "v.",
      "def": "Mislead.",
      "trans": "误导",
      "speakText": "misguide"
    },
    {
      "key": "alleviate",
      "pos": "v.",
      "def": "Make (suffering, deficiency, or a problem) less severe.",
      "trans": "缓解，减轻",
      "speakText": "alleviate"
    },
    {
      "key": "motivate",
      "pos": "v.",
      "def": "Provide (someone) with a motive for doing something.",
      "trans": "激发，促使",
      "speakText": "motivate"
    },
    {
      "key": "effective",
      "pos": "adj.",
      "def": "Successful in producing a desired or intended result.",
      "trans": "有效的",
      "speakText": "effective"
    },
    {
      "key": "landfill",
      "pos": "n.",
      "def": "A place to dispose of refuse and other waste material.",
      "trans": "垃圾填埋场",
      "speakText": "landfill"
    },
    {
      "key": "trash",
      "pos": "n.",
      "def": "Discarded matter; refuse.",
      "trans": "垃圾，废物",
      "speakText": "trash"
    },
    {
      "key": "craft",
      "pos": "v.",
      "def": "Exercise skill in making (something).",
      "trans": "精心制作",
      "speakText": "craft"
    },
    {
      "key": "probe",
      "pos": "v.",
      "def": "Physically explore or examine (something) with the hands or an instrument.",
      "trans": "探查，探测",
      "speakText": "probe"
    },
    {
      "key": "peers",
      "pos": "n.",
      "def": "A person of the same age, status, or ability as another specified person.",
      "trans": "同辈，同伴",
      "speakText": "peers"
    },
    {
      "key": "loyalty",
      "pos": "n.",
      "def": "A strong feeling of support or allegiance.",
      "trans": "忠诚度",
      "speakText": "loyalty"
    },
    {
      "key": "charge",
      "pos": "n.",
      "def": "Responsibility for the care or control of someone or something.",
      "trans": "负责，掌控 (如: take charge of)",
      "speakText": "charge"
    },
    {
      "key": "puzzle feeders",
      "pos": "n.",
      "def": "Devices that require animals to solve a problem or perform a task to obtain food, used for environmental enrichment.",
      "trans": "玩具喂食器，益智喂食器",
      "speakText": "puzzle feeders"
    }
  ],
  "chart": {
    "type": "bar",
    "title": "Impact of Enrichment on Captive Animals",
    "description": "Comparison of animal well-being indicators between standard lavish enclosures (free food) and enriched environments (puzzle feeders).",
    "labels": [
      "Boredom & Stress",
      "Brain Activity",
      "Social Interaction"
    ],
    "datasets": [
      {
        "label": "Lavish Enclosure (Free Food)",
        "data": [
          85,
          30,
          40
        ],
        "borderColor": "#f43f5e",
        "backgroundColor": "rgba(244, 63, 94, 0.7)"
      },
      {
        "label": "Enriched Environment (Puzzles)",
        "data": [
          20,
          85,
          90
        ],
        "borderColor": "#10b981",
        "backgroundColor": "rgba(16, 185, 129, 0.7)"
      }
    ],
    "yBeginAtZero": true,
    "yMin": 0,
    "yMax": 100,
    "yAxisTitle": "Observed Frequency Score (0-100)",
    "insights": [
      {
        "icon": "🧠",
        "title": "Mental Stimulation",
        "text": "Puzzle feeders significantly boost brain activity by forcing animals to use their natural instincts."
      },
      {
        "icon": "📉",
        "title": "Stress Reduction",
        "text": "An effortless life leads to high stress, whereas manageable challenges dramatically reduce boredom."
      }
    ]
  },
  "quiz": {
    "title": "Knowledge Check",
    "questions": [
      {
        "id": "q-1",
        "type": "tfng",
        "mode": "TFNG",
        "prompt": "True / False / Not Given",
        "statement": "Providing captive animals with an effortless life in lavish enclosures is a scientifically proven way to improve their mental health.",
        "answer": "FALSE",
        "rationale": {
          "en": "Paragraph A states: 'A completely effortless life actually harms an animal’s mental well-being...' The statement contradicts the text.",
          "zh": "【反义词陷阱】原文 Paragraph A 明确指出“完全不费吹灰之力的生活实际上会损害 (harms) 动物的心理健康”，而题目中使用了 improve (改善)，意思完全相反。"
        },
        "evidenceRefs": [
          "Paragraph A"
        ]
      },
      {
        "id": "q-2",
        "type": "tfng",
        "mode": "TFNG",
        "prompt": "True / False / Not Given",
        "statement": "Monkeys are generally faster at solving puzzle feeders than other social animals in zoos.",
        "answer": "NOT_GIVEN",
        "rationale": {
          "en": "Paragraph C mentions monkeys solving puzzle feeders and social animals copying behavior, but it never compares the speed between monkeys and other animals.",
          "zh": "【无中生有】原文 Paragraph C 提到了猴子 (monkeys) 和解谜 (solving puzzle feeders)，但绝对没有比较“猴子比其他动物更快 (faster)”。"
        },
        "evidenceRefs": [
          "Paragraph C"
        ]
      },
      {
        "id": "q-3",
        "type": "multiple_choice",
        "selectionMode": "single",
        "prompt": "According to Paragraph A, what is the modern scientific view on giving animals 'free food'?",
        "options": [
          {
            "id": "A",
            "text": "It effectively eases the daily lives of animals, making them behave naturally."
          },
          {
            "id": "B",
            "text": "It misguides animals into forgetting how to interact with their peers."
          },
          {
            "id": "C",
            "text": "It is less beneficial for an animal's psychological health than previously thought."
          },
          {
            "id": "D",
            "text": "It is the primary reason why certain wild species become endangered."
          }
        ],
        "correctOptionIds": [
          "C"
        ],
        "rationale": {
          "en": "Paragraph A explains that scientists confirm the idea of free food easing lives misguides the public, and it actually harms mental well-being. 'Less beneficial' matches 'harms'.",
          "zh": "【同义替换】正确项C 'less beneficial' 完美对应了原文的 'harms' 和打破过去的错误认知。干扰项A包含原词 'ease'，干扰项B包含原词 'misguide'，但均属于偷换概念。"
        },
        "evidenceRefs": [
          "Paragraph A"
        ]
      },
      {
        "id": "q-4",
        "type": "completion",
        "subtype": "summary",
        "prompt": "Summary Completion",
        "instruction": "Complete the summary below. Choose ONE WORD ONLY from the passage for each answer.",
        "contentTemplate": "Social Learning in Zoos\n\nPuzzle feeders do more than just feed animals; they encourage social behavior. When an animal successfully solves a puzzle, other individuals, known as their {{blank1}}, observe and imitate this success. Researchers note that this shared activity is highly beneficial, as it builds deeper emotional connections and increases group {{blank2}} within the animal community.",
        "blanks": [
          {
            "id": "blank1",
            "acceptedAnswers": [
              "peers"
            ],
            "wordLimit": 1,
            "caseSensitive": false,
            "posHint": "noun"
          },
          {
            "id": "blank2",
            "acceptedAnswers": [
              "loyalty"
            ],
            "wordLimit": 1,
            "caseSensitive": false,
            "posHint": "noun"
          }
        ],
        "rationale": {
          "en": "For blank 1, 'other individuals' matches 'its peers' in Paragraph C. For blank 2, 'increases group' matches 'strengthens group loyalty' in Paragraph C.",
          "zh": "【语法与替换解析】第一空：题目 'other individuals, known as their...' 对应原文 'its peers'（它的同伴）。第二空：题目 'increases group ______' 对应原文 'strengthens group loyalty'，strengthen 等于 increase，所以填 loyalty。"
        },
        "evidenceRefs": [
          "Paragraph C"
        ]
      }
    ]
  }
}
